{
  "formColumnSetting": [
    {
      "columnType": "varchar(80)",
      "component": "t-input",
      "componentParam": "",
      "componentSource": null,
      "defaultValue": "",
      "disabled": true,
      "field": "maintenance_plan_code",
      "fieldType": null,
      "id": "1979249244809189376",
      "isDisabled": true,
      "isKeyField": true,
      "isMutiple": false,
      "isRequired": true,
      "isVisible": true,
      "keyField": true,
      "label": "保养计划代码",
      "mutiple": false,
      "placeholder": null,
      "required": true,
      "seq": 1,
      "verifyExp": "",
      "visible": true
    },
    {
      "columnType": "varchar(240)",
      "component": "t-input",
      "componentParam": "",
      "componentSource": null,
      "defaultValue": "",
      "disabled": true,
      "field": "maintenance_plan_name",
      "fieldType": null,
      "id": "6430913614447872000",
      "isDisabled": true,
      "isKeyField": false,
      "isMutiple": false,
      "isRequired": true,
      "isVisible": true,
      "keyField": false,
      "label": "保养计划名称",
      "mutiple": false,
      "placeholder": null,
      "required": true,
      "seq": 2,
      "verifyExp": "",
      "visible": true
    },
    {
      "columnType": "varchar(80)",
      "component": "t-radio-group",
      "componentParam": "",
      "componentSource": {
        "customDict": {
          "dicData": [
            {
              "label": "周期保养",
              "value": "PERIOD"
            },
            {
              "label": "使用次数",
              "value": "USETIME"
            }
          ]
        },
        "dataTable": {
          "conditionData": [],
          "mapBusinessDomain": "",
          "mapTable": "",
          "showField": "",
          "valueField": ""
        },
        "sourceType": "customDict"
      },
      "defaultValue": "",
      "disabled": false,
      "field": "maintenance_plan_type",
      "fieldType": null,
      "id": "5781640216176422912",
      "isDisabled": false,
      "isKeyField": false,
      "isMutiple": false,
      "isRequired": true,
      "isVisible": true,
      "keyField": false,
      "label": "保养计划方式",
      "mutiple": false,
      "placeholder": null,
      "required": true,
      "seq": 3,
      "verifyExp": "",
      "visible": true
    },
    {
      "columnType": "datetime(4)",
      "component": "t-date-picker",
      "componentParam": "",
      "componentSource": null,
      "defaultValue": "",
      "disabled": false,
      "field": "datetime_effect",
      "fieldType": null,
      "id": "7582449786451361792",
      "isDisabled": false,
      "isKeyField": false,
      "isMutiple": false,
      "isRequired": true,
      "isVisible": true,
      "keyField": false,
      "label": "生效时间",
      "mutiple": false,
      "placeholder": null,
      "required": true,
      "seq": 4,
      "verifyExp": "",
      "visible": true
    },
    {
      "columnType": "int",
      "component": "t-input-number",
      "componentParam": "",
      "componentSource": null,
      "defaultValue": "",
      "disabled": false,
      "field": "day_maintenance_period",
      "fieldType": null,
      "id": "8079611604183496704",
      "isDisabled": false,
      "isKeyField": false,
      "isMutiple": false,
      "isRequired": true,
      "isVisible": true,
      "keyField": false,
      "label": "保养周期（天）",
      "mutiple": false,
      "placeholder": null,
      "required": false,
      "seq": 5,
      "verifyExp": "",
      "visible": true
    },
    {
      "columnType": "int",
      "component": "t-input-number",
      "componentParam": "",
      "componentSource": null,
      "defaultValue": "",
      "disabled": false,
      "field": "day_early_warn",
      "fieldType": null,
      "id": "1957731539453566976",
      "isDisabled": false,
      "isKeyField": false,
      "isMutiple": false,
      "isRequired": true,
      "isVisible": true,
      "keyField": false,
      "label": "预警提前期（天）",
      "mutiple": false,
      "placeholder": null,
      "required": false,
      "seq": 6,
      "verifyExp": "",
      "visible": true
    },
    {
      "columnType": "int",
      "component": "t-input-number",
      "componentParam": "",
      "componentSource": null,
      "defaultValue": "",
      "disabled": false,
      "field": "hour_run",
      "fieldType": null,
      "id": "4228583883284498432",
      "isDisabled": false,
      "isKeyField": false,
      "isMutiple": false,
      "isRequired": true,
      "isVisible": true,
      "keyField": false,
      "label": "使用次数",
      "mutiple": false,
      "placeholder": null,
      "required": false,
      "seq": 7,
      "verifyExp": "",
      "visible": true
    },
    {
      "columnType": "int",
      "component": "t-input-number",
      "componentParam": "",
      "componentSource": null,
      "defaultValue": "",
      "disabled": false,
      "field": "hour_run_early",
      "fieldType": null,
      "id": "2861171201225009152",
      "isDisabled": false,
      "isKeyField": false,
      "isMutiple": false,
      "isRequired": true,
      "isVisible": true,
      "keyField": false,
      "label": "提前次数",
      "mutiple": false,
      "placeholder": null,
      "required": false,
      "seq": 8,
      "verifyExp": "",
      "visible": true
    },
    {
      "columnType": "String",
      "component": "t-radio-group",
      "componentSource": {
        "sourceType": "customDict",
        "customDict": {
          "dicData": [
            {
              "label": "关联模具类型",
              "value": "mouldType"
            },
            {
              "label": "关联模具",
              "value": "mould"
            }
          ]
        },
        "dataTable": {
          "mapBusinessDomain": "",
          "mapTable": "",
          "conditionData": [],
          "valueField": "",
          "showField": ""
        }
      },
      "defaultValue": "mouldType",
      "disabled": false,
      "field": "relateType",
      "fieldType": null,
      "id": "relateType",
      "isDisabled": false,
      "isKeyField": false,
      "isMutiple": false,
      "isRequired": true,
      "isVisible": true,
      "keyField": false,
      "label": "关联类型",
      "mutiple": false,
      "placeholder": null,
      "required": false,
      "seq": 2,
      "verifyExp": "",
      "visible": true
    },
    {
      "columnType": "varchar(80)",
      "component": "bcmp-select-param",
      "componentParam": "E_MOULD_TYPE",
      "componentSource": null,
      "defaultValue": "",
      "disabled": false,
      "field": "mould_type",
      "fieldType": null,
      "id": "1191873293498304512",
      "isDisabled": false,
      "isKeyField": false,
      "isMutiple": false,
      "isRequired": true,
      "isVisible": true,
      "keyField": false,
      "label": "模具类型",
      "mutiple": false,
      "placeholder": null,
      "required": false,
      "seq": 9,
      "verifyExp": "",
      "visible": true
    },
    {
      "columnType": "bigint",
      "component": "bcmp-select-business",
      "componentParam": "mould",
      "componentSource": null,
      "defaultValue": "",
      "disabled": false,
      "field": "m_mould_id",
      "fieldType": null,
      "id": "6372160288314134528",
      "isDisabled": false,
      "isKeyField": false,
      "isMutiple": false,
      "isRequired": true,
      "isVisible": true,
      "keyField": false,
      "label": "模具",
      "mutiple": false,
      "placeholder": null,
      "required": false,
      "seq": 10,
      "verifyExp": "",
      "visible": true
    },
    {
      "columnType": "int",
      "component": "t-switch",
      "componentParam": "",
      "componentSource": null,
      "defaultValue": "",
      "disabled": false,
      "field": "state",
      "fieldType": null,
      "id": "6848017972128808960",
      "isDisabled": false,
      "isKeyField": false,
      "isMutiple": false,
      "isRequired": false,
      "isVisible": true,
      "keyField": false,
      "label": "启用状态",
      "mutiple": false,
      "placeholder": null,
      "required": false,
      "seq": 11,
      "verifyExp": "",
      "visible": true
    },
    {
      "columnType": "datetime(4)",
      "component": "t-input",
      "componentParam": "",
      "componentSource": null,
      "defaultValue": "",
      "disabled": false,
      "field": "time_create",
      "fieldType": null,
      "id": "4750236166081570816",
      "isDisabled": false,
      "isKeyField": false,
      "isMutiple": false,
      "isRequired": false,
      "isVisible": false,
      "keyField": false,
      "label": "创建时间",
      "mutiple": false,
      "placeholder": null,
      "required": false,
      "seq": 12,
      "verifyExp": "",
      "visible": false
    },
    {
      "columnType": "bigint",
      "component": "t-input",
      "componentParam": "",
      "componentSource": null,
      "defaultValue": "",
      "disabled": false,
      "field": "id",
      "fieldType": null,
      "id": "6294374149532706816",
      "isDisabled": false,
      "isKeyField": false,
      "isMutiple": false,
      "isRequired": false,
      "isVisible": false,
      "keyField": false,
      "label": "",
      "mutiple": false,
      "placeholder": null,
      "required": false,
      "seq": 13,
      "verifyExp": "",
      "visible": false
    },
    {
      "columnType": "bigint",
      "component": "t-input",
      "componentParam": "",
      "componentSource": null,
      "defaultValue": "",
      "disabled": false,
      "field": "m_asset_type_id",
      "fieldType": null,
      "id": "196172220756541440",
      "isDisabled": false,
      "isKeyField": false,
      "isMutiple": false,
      "isRequired": false,
      "isVisible": false,
      "keyField": false,
      "label": "资产类型表ID",
      "mutiple": false,
      "placeholder": null,
      "required": false,
      "seq": 14,
      "verifyExp": "",
      "visible": false
    },
    {
      "columnType": "bigint",
      "component": "t-input",
      "componentParam": "",
      "componentSource": null,
      "defaultValue": "",
      "disabled": false,
      "field": "m_asset_brand_id",
      "fieldType": null,
      "id": "7194000198495977472",
      "isDisabled": false,
      "isKeyField": false,
      "isMutiple": false,
      "isRequired": false,
      "isVisible": false,
      "keyField": false,
      "label": "资产品牌表ID",
      "mutiple": false,
      "placeholder": null,
      "required": false,
      "seq": 15,
      "verifyExp": "",
      "visible": false
    },
    {
      "columnType": "bigint",
      "component": "t-input",
      "componentParam": "",
      "componentSource": null,
      "defaultValue": "",
      "disabled": false,
      "field": "m_asset_model_id",
      "fieldType": null,
      "id": "5356558238514077696",
      "isDisabled": false,
      "isKeyField": false,
      "isMutiple": false,
      "isRequired": false,
      "isVisible": false,
      "keyField": false,
      "label": "资产型号表ID",
      "mutiple": false,
      "placeholder": null,
      "required": false,
      "seq": 16,
      "verifyExp": "",
      "visible": false
    },
    {
      "columnType": "varchar(80)",
      "component": "t-input",
      "componentParam": "",
      "componentSource": null,
      "defaultValue": "",
      "disabled": false,
      "field": "creator",
      "fieldType": null,
      "id": "658595641727797248",
      "isDisabled": false,
      "isKeyField": false,
      "isMutiple": false,
      "isRequired": false,
      "isVisible": false,
      "keyField": false,
      "label": "创建人",
      "mutiple": false,
      "placeholder": null,
      "required": false,
      "seq": 17,
      "verifyExp": "",
      "visible": false
    },
    {
      "columnType": "datetime(4)",
      "component": "t-input",
      "componentParam": "",
      "componentSource": null,
      "defaultValue": "",
      "disabled": false,
      "field": "time_modified",
      "fieldType": null,
      "id": "9147958099678668800",
      "isDisabled": false,
      "isKeyField": false,
      "isMutiple": false,
      "isRequired": false,
      "isVisible": false,
      "keyField": false,
      "label": "修改时间",
      "mutiple": false,
      "placeholder": null,
      "required": false,
      "seq": 18,
      "verifyExp": "",
      "visible": false
    },
    {
      "columnType": "varchar(80)",
      "component": "t-input",
      "componentParam": "",
      "componentSource": null,
      "defaultValue": "",
      "disabled": false,
      "field": "modifier",
      "fieldType": null,
      "id": "3019427964243161088",
      "isDisabled": false,
      "isKeyField": false,
      "isMutiple": false,
      "isRequired": false,
      "isVisible": false,
      "keyField": false,
      "label": "修改人",
      "mutiple": false,
      "placeholder": null,
      "required": false,
      "seq": 19,
      "verifyExp": "",
      "visible": false
    },
    {
      "columnType": "bigint",
      "component": "t-input",
      "componentParam": "",
      "componentSource": null,
      "defaultValue": "",
      "disabled": false,
      "field": "eid",
      "fieldType": null,
      "id": "7989769675184011264",
      "isDisabled": false,
      "isKeyField": false,
      "isMutiple": false,
      "isRequired": false,
      "isVisible": false,
      "keyField": false,
      "label": "企业ID",
      "mutiple": false,
      "placeholder": null,
      "required": false,
      "seq": 20,
      "verifyExp": "",
      "visible": false
    },
    {
      "columnType": "bigint",
      "component": "t-input",
      "componentParam": "",
      "componentSource": null,
      "defaultValue": "",
      "disabled": false,
      "field": "oid",
      "fieldType": null,
      "id": "3195778080208447488",
      "isDisabled": false,
      "isKeyField": false,
      "isMutiple": false,
      "isRequired": false,
      "isVisible": false,
      "keyField": false,
      "label": "组织ID",
      "mutiple": false,
      "placeholder": null,
      "required": false,
      "seq": 21,
      "verifyExp": "",
      "visible": false
    }
  ]
}